lv_velodyne/__init__.py
lv_velodyne/interface.py
lv_velodyne/models.py
lv_velodyne/objects.py
lv_velodyne/udp_parsing.py
lv_velodyne-0.1.0.dist-info/WHEEL
lv_velodyne-0.1.0.dist-info/METADATA
lv_velodyne-0.1.0.dist-info/RECORD
