Metadata-Version: 2.1
Name: lv_velodyne
Version: 0.1.0
Summary: A package for interfacing with the Velodyne LiDAR Pucks.
Author: Brian Leist
Requires-Python: >=3.7
Requires-Dist: dataclasses_json
Requires-Dist: lv-physics
Requires-Dist: numpy
Requires-Dist: scipy
Requires-Dist: black ; extra == "dev"
Requires-Dist: bump2version ; extra == "dev"
Requires-Dist: isort ; extra == "dev"
Requires-Dist: ipython ; extra == "dev"
Requires-Dist: matplotlib ; extra == "dev"
Requires-Dist: pytest ; extra == "dev"
Provides-Extra: dev
